what2_time/__init__.py
what2_time/counter.py
what2_time/py.typed
what2_time/timer.py
what2_time-0.3.1.dist-info/METADATA
what2_time-0.3.1.dist-info/WHEEL
what2_time-0.3.1.dist-info/RECORD
