Metadata-Version: 2.1
Name: what2-time
Version: 0.3.1
Summary: Reusable timing code that handles unit conversion, pretty printing time, total of repeat and re-entrant timers.
Home-page: https://github.com/alwaysmpe/what2_time
License: MIT
Author: Marc Edwards
Author-email: marc@mlwhat.com
Requires-Python: >=3.12,<4.0
Classifier: Development Status :: 3 - Alpha
Classifier: License :: OSI Approved :: MIT License
Classifier: Programming Language :: Python :: 3
Classifier: Programming Language :: Python :: 3.12
Project-URL: Repository, https://github.com/alwaysmpe/what2_time
